odoo10_addon_membership_withdrawal-10.0.1.0.0-py2.7-nspkg.pth
odoo/addons/membership_withdrawal/README.rst
odoo/addons/membership_withdrawal/__init__.py
odoo/addons/membership_withdrawal/__manifest__.py
odoo/addons/membership_withdrawal/data/membership_withdrawal_reason_data.xml
odoo/addons/membership_withdrawal/i18n/es.po
odoo/addons/membership_withdrawal/models/__init__.py
odoo/addons/membership_withdrawal/models/membership_line.py
odoo/addons/membership_withdrawal/models/membership_withdrawal_reason.py
odoo/addons/membership_withdrawal/models/res_partner.py
odoo/addons/membership_withdrawal/security/ir.model.access.csv
odoo/addons/membership_withdrawal/static/description/icon.png
odoo/addons/membership_withdrawal/tests/__init__.py
odoo/addons/membership_withdrawal/tests/test_membership.py
odoo/addons/membership_withdrawal/views/membership_withdrawal_reason_view.xml
odoo/addons/membership_withdrawal/views/res_partner_view.xml
odoo10_addon_membership_withdrawal-10.0.1.0.0.dist-info/DESCRIPTION.rst
odoo10_addon_membership_withdrawal-10.0.1.0.0.dist-info/METADATA
odoo10_addon_membership_withdrawal-10.0.1.0.0.dist-info/RECORD
odoo10_addon_membership_withdrawal-10.0.1.0.0.dist-info/WHEEL
odoo10_addon_membership_withdrawal-10.0.1.0.0.dist-info/metadata.json
odoo10_addon_membership_withdrawal-10.0.1.0.0.dist-info/namespace_packages.txt
odoo10_addon_membership_withdrawal-10.0.1.0.0.dist-info/top_level.txt
